odoo/addons/report_hotel_reservation/README.rst
odoo/addons/report_hotel_reservation/__init__.py
odoo/addons/report_hotel_reservation/__manifest__.py
odoo/addons/report_hotel_reservation/LICENSE/LICENSE
odoo/addons/report_hotel_reservation/i18n/es.po
odoo/addons/report_hotel_reservation/i18n/fr.po
odoo/addons/report_hotel_reservation/i18n/fr_BE.po
odoo/addons/report_hotel_reservation/i18n/it.po
odoo/addons/report_hotel_reservation/i18n/report_hotel_reservation.pot
odoo/addons/report_hotel_reservation/i18n/sv.po
odoo/addons/report_hotel_reservation/models/__init__.py
odoo/addons/report_hotel_reservation/models/report_hotel_reservation.py
odoo/addons/report_hotel_reservation/readme/CONTRIBUTORS.rst
odoo/addons/report_hotel_reservation/readme/DESCRIPTION.rst
odoo/addons/report_hotel_reservation/security/ir.model.access.csv
odoo/addons/report_hotel_reservation/static/description/icon.png
odoo/addons/report_hotel_reservation/static/description/index.html
odoo/addons/report_hotel_reservation/static/description/sbres.png
odoo/addons/report_hotel_reservation/static/description/serpent.png
odoo/addons/report_hotel_reservation/views/report_hotel_reservation_view.xml
odoo14_addon_report_hotel_reservation-14.0.1.0.1.dev9.dist-info/METADATA
odoo14_addon_report_hotel_reservation-14.0.1.0.1.dev9.dist-info/WHEEL
odoo14_addon_report_hotel_reservation-14.0.1.0.1.dev9.dist-info/top_level.txt
odoo14_addon_report_hotel_reservation-14.0.1.0.1.dev9.dist-info/RECORD
